docs/Makefile
docs/source/adding.rst
docs/source/changelog.rst
docs/source/conf.py
docs/source/contributing.rst
docs/source/credits.rst
docs/source/index.rst
docs/source/installation.rst
docs/source/_static/favicon.ico
docs/source/_static/pyproximal.png
docs/source/_static/pyproximal_b.png
docs/source/_static/style.css
docs/source/_templates/layout.html
docs/source/_templates/autosummary/base.rst
docs/source/_templates/autosummary/class.rst
docs/source/_templates/autosummary/exception.rst
docs/source/_templates/autosummary/function.rst
docs/source/_templates/autosummary/module.rst
docs/source/api/index.rst
examples/README.txt
examples/plot_concave_penalties.py
examples/plot_indicators.py
examples/plot_norms.py
examples/plot_quadratic.py
pyproximal/ProxOperator.py
pyproximal/__init__.py
pyproximal/version.py
pyproximal/optimization/__init__.py
pyproximal/optimization/bregman.py
pyproximal/optimization/palm.py
pyproximal/optimization/pnp.py
pyproximal/optimization/primal.py
pyproximal/optimization/primaldual.py
pyproximal/optimization/segmentation.py
pyproximal/optimization/sr3.py
pyproximal/projection/AffineSet.py
pyproximal/projection/Box.py
pyproximal/projection/Euclidean.py
pyproximal/projection/Hankel.py
pyproximal/projection/Intersection.py
pyproximal/projection/L0.py
pyproximal/projection/L1.py
pyproximal/projection/Nuclear.py
pyproximal/projection/Simplex.py
pyproximal/projection/__init__.py
pyproximal/proximal/AffineSet.py
pyproximal/proximal/Box.py
pyproximal/proximal/ETP.py
pyproximal/proximal/Euclidean.py
pyproximal/proximal/Geman.py
pyproximal/proximal/Hankel.py
pyproximal/proximal/Huber.py
pyproximal/proximal/Intersection.py
pyproximal/proximal/L0.py
pyproximal/proximal/L1.py
pyproximal/proximal/L2.py
pyproximal/proximal/L21.py
pyproximal/proximal/L21_plus_L1.py
pyproximal/proximal/Log.py
pyproximal/proximal/Nonlinear.py
pyproximal/proximal/Nuclear.py
pyproximal/proximal/Orthogonal.py
pyproximal/proximal/Quadratic.py
pyproximal-0.10.0.dist-info/LICENSE.md
pyproximal-0.10.0.dist-info/METADATA
pyproximal-0.10.0.dist-info/WHEEL
pyproximal-0.10.0.dist-info/top_level.txt
pyproximal-0.10.0.dist-info/RECORD
