Metadata-Version: 2.1
Name: pyproximal
Version: 0.10.0
Summary: Python library implementing proximal operators to solve non-smooth, constrained convex problems with proximal algorithms
Author-email: Matteo Ravasi <matteoravasi@gmail.com>
License:                    GNU LESSER GENERAL PUBLIC LICENSE
Keywords: algebra,inverse problems,proximal,convex optimization,large-scale optimization
Classifier: Development Status :: 4 - Beta
Classifier: Intended Audience :: Developers
Classifier: Intended Audience :: Science/Research
Classifier: Intended Audience :: Education
Classifier: License :: OSI Approved :: GNU Lesser General Public License v3 (LGPLv3)
Classifier: Natural Language :: English
Classifier: Operating System :: OS Independent
Classifier: Programming Language :: Python :: 3 :: Only
Classifier: Programming Language :: Python :: 3.8
Classifier: Programming Language :: Python :: 3.9
Classifier: Programming Language :: Python :: 3.10
Classifier: Topic :: Scientific/Engineering :: Mathematics
License-File: LICENSE.md
Requires-Dist: numpy>=1.21.0
Requires-Dist: scipy>=1.11.0
Requires-Dist: pylops>=2.0.0
Provides-Extra: advanced
Requires-Dist: llvmlite; extra == "advanced"
Requires-Dist: numba; extra == "advanced"
